fs_leonid/__init__.py
fs_leonid/admin.py
fs_leonid/apps.py
fs_leonid/models.py
fs_leonid/settings.py
fs_leonid/urls.py
fs_leonid/views.py
fs_leonid/fixtures/initial_data.json
fs_leonid/locale/ru/LC_MESSAGES/django.mo
fs_leonid/locale/ru/LC_MESSAGES/django.po
fs_leonid/migrations/0001_initial.py
fs_leonid/migrations/0002_leofile.py
fs_leonid/migrations/0003_load_initial_data.py
fs_leonid/migrations/__init__.py
django_fs_leonid-1.0.0.dist-info/LICENSE
django_fs_leonid-1.0.0.dist-info/METADATA
django_fs_leonid-1.0.0.dist-info/WHEEL
django_fs_leonid-1.0.0.dist-info/top_level.txt
django_fs_leonid-1.0.0.dist-info/RECORD
