Metadata-Version: 2.1
Name: django-fs-leonid
Version: 1.0.0
Summary: The Django-related reusable app provides the ability to create and store in a database files such as robots.txt, sitemap.xml and so on.
Home-page: https://github.com/fogstream/django-fs-leonid
Author: Yuri Lya
Author-email: yuri.lya@fogstream.ru
License: The MIT License (MIT)
Platform: UNKNOWN
Classifier: Development Status :: 5 - Production/Stable
Classifier: Environment :: Web Environment
Classifier: Intended Audience :: Developers
Classifier: Operating System :: OS Independent
Classifier: Programming Language :: Python
Classifier: Framework :: Django
Requires-Python: >=3.6
